ffmpeg_toolkit/__init__.py
ffmpeg_toolkit/ffmpeg_toolkit.py
ffmpeg_toolkit/ffmpeg_toolkit_core.py
ffmpeg_toolkit/ffmpeg_types.py
ffmpeg_toolkit-0.4.1.dist-info/licenses/LICENSE
ffmpeg_toolkit-0.4.1.dist-info/METADATA
ffmpeg_toolkit-0.4.1.dist-info/WHEEL
ffmpeg_toolkit-0.4.1.dist-info/top_level.txt
ffmpeg_toolkit-0.4.1.dist-info/RECORD
