Metadata-Version: 2.4
Name: ffmpeg-toolkit
Version: 0.4.1
Summary: A comprehensive Python toolkit for video processing using FFmpeg
Home-page: https://github.com/superyngo/ffmpeg_toolkit
Author: Wenyang Tai
Author-email: superyngo@gmail.com
Requires-Python: >=3.9
License-File: LICENSE
Requires-Dist: pydantic>=2.11.3
Provides-Extra: dev
Requires-Dist: pytest>=7.0.0; extra == "dev"
Requires-Dist: pytest-cov>=4.0.0; extra == "dev"
Dynamic: author
Dynamic: author-email
Dynamic: home-page
Dynamic: license-file
Dynamic: requires-python
